__init__.py
image_network_library/__init__.py
image_network_library/networks.py
image_network_library/preprocessing.py
image_network_library/visualization.py
image_network_library-1.0.2.dist-info/LICENSE
image_network_library-1.0.2.dist-info/METADATA
image_network_library-1.0.2.dist-info/WHEEL
image_network_library-1.0.2.dist-info/top_level.txt
image_network_library-1.0.2.dist-info/RECORD
