Metadata-Version: 2.1
Name: image-network-library
Version: 1.0.2
Summary: A image neural network lib for measurements and skeletons
Home-page: https://github.com/ShaziaSulemane/a22207399
Author: Shazia Sulemane
Author-email: shazia.sulemane@gmail.com
License: MIT
Platform: UNKNOWN
License-File: LICENSE
